bam2plot/__init__.py
bam2plot/main.py
bam2plot-0.3.7.dist-info/LICENSE
bam2plot-0.3.7.dist-info/METADATA
bam2plot-0.3.7.dist-info/WHEEL
bam2plot-0.3.7.dist-info/entry_points.txt
bam2plot-0.3.7.dist-info/top_level.txt
bam2plot-0.3.7.dist-info/RECORD
