Metadata-Version: 2.1
Name: bam2plot
Version: 0.3.7
Summary: Plot of coverage from bam file
Home-page: https://github.com/willros/bam2plot
Author: William Rosenbaum
Author-email: william.rosenbaum@gmail.com
License: MIT
Requires-Python: >=3.10
License-File: LICENSE
Requires-Dist: pysam==0.22.0
Requires-Dist: seaborn==0.13.2
Requires-Dist: polars==0.20.15
Requires-Dist: mappy==2.28
Requires-Dist: pyfastx
Requires-Dist: pyarrow
